simple_proxy/__init__.py
simple_proxy/proxied_selenium_pool.py
simple_proxy/proxied_session.py
simple_proxy/proxy_info.py
simple_proxy/proxy_pool.py
simple_proxy/selenium_helper.py
simple_proxy/user_agents.py
simple_proxy2/__init__.py
simple_proxy2/proxy_manager.py
simple_proxy2/data/__init__.py
simple_proxy2/data/observable.py
simple_proxy2/data/observer.py
simple_proxy2/data/proxy.py
simple_proxy2/data/proxy_info.py
simple_proxy2/pool/__init__.py
simple_proxy2/pool/proxy_pool.py
simple_proxy2/pool/tools.py
simple_proxy2/tools/__init__.py
simple_proxy2/tools/random_user_agent.py
simple_proxy2/tools/simple_timer.py
simple_proxy3/__init__.py
simple_proxy3/proxy.py
simple_proxy3/proxy_info.py
simple_proxy3/proxy_manager.py
simple_proxy3/proxy_pool.py
simple_proxy3/observables/__init__.py
simple_proxy3/observables/observable.py
simple_proxy3/tools/__init__.py
simple_proxy3/tools/random_user_agent.py
simple_proxy3/tools/simple_timer.py
tests/__init__.py
tests/test_observables.py
tests/test_proxy.py
tests/test_proxy_info.py
tests/test_proxy_manager.py
tests/test_proxy_pool.py
simple_proxy_wysohn-0.4.3.dist-info/LICENSE
simple_proxy_wysohn-0.4.3.dist-info/METADATA
simple_proxy_wysohn-0.4.3.dist-info/WHEEL
simple_proxy_wysohn-0.4.3.dist-info/top_level.txt
simple_proxy_wysohn-0.4.3.dist-info/RECORD
