Metadata-Version: 2.1
Name: simple-proxy-wysohn
Version: 0.4.3
Summary: Simple proxy library
Author: wysohn
Author-email: wysohn2002@naver.com
Requires-Python: >=3.6
License-File: LICENSE
